{
  "type": "Feature",
  "properties": {
    "gn:admin1_code":"BO",
    "gn:asciiname":"Sint Joris",
    "gn:country_code":"BQ",
    "gn:dem":39,
    "gn:feature_class":"P",
    "gn:feature_code":"PPLL",
    "gn:name":"Sint Joris",
    "gn:population":0,
    "gn:timezone":"America/Kralendijk",
    "iso:country":"BQ",
    "wof:name":"Sint Joris",
    "wof:placetype":"locality"
},
  "geometry": {"coordinates":[-68.33333,12.23333],"type":"Point"}
}