{
  "type": "Feature",
  "properties": {
    "gn:admin1_code":"BO",
    "gn:asciiname":"Paradijs",
    "gn:country_code":"BQ",
    "gn:dem":20,
    "gn:feature_class":"P",
    "gn:feature_code":"PPLL",
    "gn:name":"Paradijs",
    "gn:population":0,
    "gn:timezone":"America/Kralendijk",
    "iso:country":"BQ",
    "wof:name":"Paradijs",
    "wof:placetype":"locality"
},
  "geometry": {"coordinates":[-68.23333000000001,12.15],"type":"Point"}
}