{
  "type": "Feature",
  "properties": {
    "gn:admin1_code":"BO",
    "gn:asciiname":"Onima",
    "gn:country_code":"BQ",
    "gn:dem":28,
    "gn:feature_class":"P",
    "gn:feature_code":"PPL",
    "gn:name":"Onima",
    "gn:population":0,
    "gn:timezone":"America/Kralendijk",
    "iso:country":"BQ",
    "wof:name":"Onima",
    "wof:placetype":"locality"
},
  "geometry": {"coordinates":[-68.31667,12.25],"type":"Point"}
}