{
  "type": "Feature",
  "properties": {
    "gn:admin1_code":"BO",
    "gn:asciiname":"Boven Bolivia",
    "gn:country_code":"BQ",
    "gn:dem":21,
    "gn:feature_class":"P",
    "gn:feature_code":"PPLL",
    "gn:name":"Boven Bolivia",
    "gn:population":0,
    "gn:timezone":"America/Kralendijk",
    "iso:country":"BQ",
    "wof:name":"Boven Bolivia",
    "wof:placetype":"locality"
},
  "geometry": {"coordinates":[-68.21666999999999,12.18333],"type":"Point"}
}