{
  "type": "Feature",
  "properties": {
    "gn:country":"BQ",
    "gn:fcode":"PPLL",
    "gn:pop":823,
    "iso:country":"BQ",
    "qs:name":"Golden Rock",
    "qs:photos_9r":0,
    "qs:photos_sr":0,
    "qs:pop_sr":"2",
    "wd:wordcount":61,
    "wof:name":"Golden Rock",
    "wof:placetype":"locality",
    "wof:population":823
},
  "geometry": {"coordinates":[-62.98333,17.48333],"type":"Point"}
}